{
  "name": "Janie Stephens",
  "age": 59,
  "address": {
    "street": "Jevi Glen",
    "city": "Liozne",
    "state": "HI",
    "zip": "66511"
  },
  "contact": {
    "phone": "(972) 374-7638",
    "servicePhone": "800816141"
  },
  "birthday": "1975-04-13T09:14:27.179Z",
  "ip": "180.246.135.150",
  "foo": "bar",
  "profile": {
    "about": "Cavukiv jutrov kunko puifiido wuj avwuspes aj if up refo tudonbum ito le uca bic. Vag cuj wordiza dude arupoajo karle cup vi rithu weku sas cevu ati loil kalodi. Ovis vur wijfolra gar wurwuz jafuh eh kumsok tidju jovkuhjo ebofov jadcoegu daf raphuz wepfevo ris ca at.",
    "bio": "Rov leswik acdeg kuh astik cifzama to hamdailu cuwunzo vop weiwvil ecegoje ucbaffu lal tu irmilha utviek. Wu wuggi ta hadjav cih boficzac irpi ru eh ju wimzel legos pewihufod zecvebo tah lo fe ganolgop. Tebzut sipfu jilo luzcobuho litwol giur vocwonsa uwwoh sob karkaltu vib buzeghum. Osuzumzep abureta oneraw nuc wu upion tutrap umopu pe zu coside gi gedniwod zow riv afa coehces."
  },
  "apiKey": "061809587bfd8b8d6be82f16d053f174b0e008c9345fe05153fbb416de58e996",
  "currency": {
    "code": "BWP",
    "name": "Botswana Pula"
  }
}