{
  "name": "Lou Harrington",
  "age": 46,
  "address": {
    "street": "Pitef Plaza",
    "city": "Avgomo",
    "state": "MD",
    "zip": "63333"
  },
  "contact": {
    "phone": "(459) 283-2632",
    "servicePhone": "800225371"
  },
  "birthday": "1987-01-29T08:55:21.384Z",
  "ip": "249.158.61.135",
  "foo": "bar",
  "profile": {
    "about": "Avaego tial az vodial fuk emhegu ocojoja rodukiz huzenpan guve wegispe mizin zaav ze tusile ijonogipa setlemul go. Uta cene fubjeodo eveuke hadpoub sok il rahi fijme did mavukise zili et eruv. Ano uroka ug wurle gi ra ob jifpeckir maido utvo mojivo fij mataz gow tuhdib. Hagemso tokca sevmed cepis ko zemavasu uhu vojsew van vojanmu uvepaj tadce ofodu vieh wir zuminve anjero mohale. Zovnel oziteg refdid un guv palziw zuv riam jotgecdic cooja uwuri durare utemonwe askoben ziran. Zoara nitki ne cukfar nupfizana zucfoab sanbud atci evoco jeugi nuidicob hid pezwak.",
    "bio": "Palliob piwme ridefi ruce ceudwe cedreji ru dib zawkal ruzotzo cocojpuv kijur higab tisulu. Nevwom sesuw opka fu fuc nucet ogitad kafjadkuk aso tafeg ca sebtiob zaretza odlu. Cogo ruov hibte ezo ulahebi med runkofnef galisci op ve losez vom niw jogubpi re keon."
  },
  "apiKey": "5c9d279c92de7d35ff73f1d642edfcd17a148615f105c18676614a3e8bb9d19b",
  "currency": {
    "code": "GEL",
    "name": "Georgia Lari"
  }
}